[
  {
    "id": 1,
    "name": "employment"
  },
  {
    "id": 2,
    "name": "express employment",
    "parent": 1
  },
  {
    "id": 3,
    "name": "american express employee login",
    "parent": 2,
    "size": 1
  },
  {
    "id": 4,
    "name": "express employee login",
    "parent": 2,
    "size": 1
  },
  {
    "id": 5,
    "name": "express employee pay",
    "parent": 2,
    "size": 1
  },
  {
    "id": 6,
    "name": "express employee portal",
    "parent": 2,
    "size": 1
  },
  {
    "id": 7,
    "name": "express employee w2",
    "parent": 2,
    "size": 1
  },
  {
    "id": 8,
    "name": "express employment employee login",
    "parent": 2,
    "size": 1
  },
  {
    "id": 9,
    "name": "express employment login",
    "parent": 2,
    "size": 1
  },
  {
    "id": 10,
    "name": "express employment login w2",
    "parent": 2,
    "size": 1
  },
  {
    "id": 11,
    "name": "express employment pay schedule",
    "parent": 2,
    "size": 1
  },
  {
    "id": 12,
    "name": "express employment portal",
    "parent": 2,
    "size": 1
  },
  {
    "id": 13,
    "name": "express employment professional login",
    "parent": 2,
    "size": 1
  },
  {
    "id": 14,
    "name": "express employment professionals employee login",
    "parent": 2,
    "size": 1
  },
  {
    "id": 15,
    "name": "att employee",
    "parent": 1
  },
  {
    "id": 16,
    "name": "atria employee login",
    "parent": 15,
    "size": 1
  },
  {
    "id": 17,
    "name": "atrialink atria employee login",
    "parent": 15,
    "size": 1
  },
  {
    "id": 18,
    "name": "atrialink employee login",
    "parent": 15,
    "size": 1
  },
  {
    "id": 19,
    "name": "att employee access",
    "parent": 15,
    "size": 1
  },
  {
    "id": 20,
    "name": "att employee benefits",
    "parent": 15,
    "size": 1
  },
  {
    "id": 21,
    "name": "att employee discount",
    "parent": 15,
    "size": 1
  },
  {
    "id": 22,
    "name": "att employee email login",
    "parent": 15,
    "size": 1
  },
  {
    "id": 23,
    "name": "att employee log in",
    "parent": 15,
    "size": 1
  },
  {
    "id": 24,
    "name": "att employee login",
    "parent": 15,
    "size": 1
  },
  {
    "id": 25,
    "name": "att employee portal",
    "parent": 15,
    "size": 1
  },
  {
    "id": 26,
    "name": "att employment verification phone number",
    "parent": 15,
    "size": 1
  },
  {
    "id": 27,
    "name": "att employment verification telephone number",
    "parent": 15,
    "size": 1
  },
  {
    "id": 28,
    "name": "coastal employment",
    "parent": 1
  },
  {
    "id": 29,
    "name": "bradenton fl employment opportunities",
    "parent": 28,
    "size": 1
  },
  {
    "id": 30,
    "name": "coast personnel staffing",
    "parent": 28,
    "size": 1
  },
  {
    "id": 31,
    "name": "coastal payroll login",
    "parent": 28,
    "size": 1
  },
  {
    "id": 32,
    "name": "coastal payroll reviews",
    "parent": 28,
    "size": 1
  },
  {
    "id": 33,
    "name": "coastal payroll services",
    "parent": 28,
    "size": 1
  },
  {
    "id": 34,
    "name": "coastal payroll solutions",
    "parent": 28,
    "size": 1
  },
  {
    "id": 35,
    "name": "coastal payrollnet",
    "parent": 28,
    "size": 1
  },
  {
    "id": 36,
    "name": "coastal payrollnet login",
    "parent": 28,
    "size": 1
  },
  {
    "id": 37,
    "name": "first coast security hermiston",
    "parent": 28,
    "size": 1
  },
  {
    "id": 38,
    "name": "gulf shores employment",
    "parent": 28,
    "size": 1
  },
  {
    "id": 39,
    "name": "long beach ny employment",
    "parent": 28,
    "size": 1
  },
  {
    "id": 40,
    "name": "seaboard employment office",
    "parent": 28,
    "size": 1
  },
  {
    "id": 41,
    "name": "big applicable",
    "parent": 1
  },
  {
    "id": 42,
    "name": "applicable large employer",
    "parent": 41,
    "size": 1
  },
  {
    "id": 43,
    "name": "applicable large employer calculation",
    "parent": 41,
    "size": 1
  },
  {
    "id": 44,
    "name": "applicable large employer calculator",
    "parent": 41,
    "size": 1
  },
  {
    "id": 45,
    "name": "applicable large employer definition",
    "parent": 41,
    "size": 1
  },
  {
    "id": 46,
    "name": "applicable large employers",
    "parent": 41,
    "size": 1
  },
  {
    "id": 47,
    "name": "big lots employee handbook",
    "parent": 41,
    "size": 1
  },
  {
    "id": 48,
    "name": "big lots employee handbook pdf",
    "parent": 41,
    "size": 1
  },
  {
    "id": 49,
    "name": "big lots employee portal",
    "parent": 41,
    "size": 1
  },
  {
    "id": 50,
    "name": "big lots employee schedule app",
    "parent": 41,
    "size": 1
  },
  {
    "id": 51,
    "name": "big y employment",
    "parent": 41,
    "size": 1
  },
  {
    "id": 52,
    "name": "big y employment application",
    "parent": 41,
    "size": 1
  },
  {
    "id": 53,
    "name": "big y employment opportunities",
    "parent": 41,
    "size": 1
  },
  {
    "id": 54,
    "name": "caesars employee",
    "parent": 1
  },
  {
    "id": 55,
    "name": "caesar payroll",
    "parent": 54,
    "size": 1
  },
  {
    "id": 56,
    "name": "caesars employee app",
    "parent": 54,
    "size": 1
  },
  {
    "id": 57,
    "name": "caesars entertainment payroll",
    "parent": 54,
    "size": 1
  },
  {
    "id": 58,
    "name": "caesars palace payroll",
    "parent": 54,
    "size": 1
  },
  {
    "id": 59,
    "name": "caesars payroll",
    "parent": 54,
    "size": 1
  },
  {
    "id": 60,
    "name": "caesars paystub",
    "parent": 54,
    "size": 1
  },
  {
    "id": 61,
    "name": "little caesars employee app",
    "parent": 54,
    "size": 1
  },
  {
    "id": 62,
    "name": "little caesars employee login",
    "parent": 54,
    "size": 1
  },
  {
    "id": 63,
    "name": "little caesars employee portal",
    "parent": 54,
    "size": 1
  },
  {
    "id": 64,
    "name": "little caesars w2 former employee",
    "parent": 54,
    "size": 1
  },
  {
    "id": 65,
    "name": "onesource login",
    "parent": 1
  },
  {
    "id": 66,
    "name": "employee onesource",
    "parent": 65,
    "size": 1
  },
  {
    "id": 67,
    "name": "employee onesource login",
    "parent": 65,
    "size": 1
  },
  {
    "id": 68,
    "name": "onesource payroll",
    "parent": 65,
    "size": 1
  },
  {
    "id": 69,
    "name": "onesource staffing login",
    "parent": 65,
    "size": 1
  },
  {
    "id": 70,
    "name": "onesource tax login",
    "parent": 65,
    "size": 1
  },
  {
    "id": 71,
    "name": "onesource tax software",
    "parent": 65,
    "size": 1
  },
  {
    "id": 72,
    "name": "payroll employment",
    "parent": 1
  },
  {
    "id": 73,
    "name": "asc payroll",
    "parent": 72,
    "size": 1
  },
  {
    "id": 74,
    "name": "asi employment",
    "parent": 72,
    "size": 1
  },
  {
    "id": 75,
    "name": "asi employment agency",
    "parent": 72,
    "size": 1
  },
  {
    "id": 76,
    "name": "asm global payroll",
    "parent": 72,
    "size": 1
  },
  {
    "id": 77,
    "name": "aso payroll",
    "parent": 72,
    "size": 1
  },
  {
    "id": 78,
    "name": "aso payroll service",
    "parent": 72,
    "size": 1
  },
  {
    "id": 79,
    "name": "aso payroll services",
    "parent": 72,
    "size": 1
  },
  {
    "id": 80,
    "name": "aspire employment",
    "parent": 72,
    "size": 1
  },
  {
    "id": 81,
    "name": "aspire payroll",
    "parent": 72,
    "size": 1
  },
  {
    "id": 82,
    "name": "aspire staffing",
    "parent": 72,
    "size": 1
  },
  {
    "id": 83,
    "name": "aspire staffing group",
    "parent": 72,
    "size": 1
  },
  {
    "id": 84,
    "name": "ati employment",
    "parent": 72,
    "size": 1
  },
  {
    "id": 85,
    "name": "cps employee",
    "parent": 1
  },
  {
    "id": 86,
    "name": "cps employee online",
    "parent": 85,
    "size": 1
  },
  {
    "id": 87,
    "name": "cps employee portal",
    "parent": 85,
    "size": 1
  },
  {
    "id": 88,
    "name": "cps payroll",
    "parent": 85,
    "size": 1
  },
  {
    "id": 89,
    "name": "cps payroll number",
    "parent": 85,
    "size": 1
  },
  {
    "id": 90,
    "name": "cps payroll services",
    "parent": 85,
    "size": 1
  },
  {
    "id": 91,
    "name": "employee online cps",
    "parent": 85,
    "size": 1
  },
  {
    "id": 92,
    "name": "employee online portal cps",
    "parent": 85,
    "size": 1
  },
  {
    "id": 93,
    "name": "my cps employee portal",
    "parent": 85,
    "size": 1
  },
  {
    "id": 94,
    "name": "harbor freight",
    "parent": 1
  },
  {
    "id": 95,
    "name": "harbor freight employee benefits",
    "parent": 94,
    "size": 1
  },
  {
    "id": 96,
    "name": "harbor freight employee portal",
    "parent": 94,
    "size": 1
  },
  {
    "id": 97,
    "name": "harbor freight employee website",
    "parent": 94,
    "size": 1
  },
  {
    "id": 98,
    "name": "harbor freight employment",
    "parent": 94,
    "size": 1
  },
  {
    "id": 99,
    "name": "harbor freight payroll",
    "parent": 94,
    "size": 1
  },
  {
    "id": 100,
    "name": "harbor freight tools employee benefits",
    "parent": 94,
    "size": 1
  },
  {
    "id": 101,
    "name": "harbor freight tools employee handbook",
    "parent": 94,
    "size": 1
  },
  {
    "id": 102,
    "name": "ashley furniture",
    "parent": 1
  },
  {
    "id": 103,
    "name": "ashley furniture employment",
    "parent": 102,
    "size": 1
  },
  {
    "id": 104,
    "name": "ashley furniture employment verification",
    "parent": 102,
    "size": 1
  },
  {
    "id": 105,
    "name": "ashley furniture wages",
    "parent": 102,
    "size": 1
  },
  {
    "id": 106,
    "name": "contact sephora",
    "parent": 102,
    "size": 1
  },
  {
    "id": 107,
    "name": "contact sephora email",
    "parent": 102,
    "size": 1
  },
  {
    "id": 108,
    "name": "sephora wage",
    "parent": 102,
    "size": 1
  },
  {
    "id": 109,
    "name": "cvs employment",
    "parent": 1
  },
  {
    "id": 110,
    "name": "cvs employee w2",
    "parent": 109,
    "size": 1
  },
  {
    "id": 111,
    "name": "cvs employment verification",
    "parent": 109,
    "size": 1
  },
  {
    "id": 112,
    "name": "cvs hr payroll",
    "parent": 109,
    "size": 1
  },
  {
    "id": 113,
    "name": "cvs human resources verification of employment",
    "parent": 109,
    "size": 1
  },
  {
    "id": 114,
    "name": "cvs my hr payroll",
    "parent": 109,
    "size": 1
  },
  {
    "id": 115,
    "name": "cvs payroll codes",
    "parent": 109,
    "size": 1
  },
  {
    "id": 116,
    "name": "cvs verification of employment",
    "parent": 109,
    "size": 1
  },
  {
    "id": 117,
    "name": "w2 cvs employee",
    "parent": 109,
    "size": 1
  },
  {
    "id": 118,
    "name": "group employment",
    "parent": 1
  },
  {
    "id": 119,
    "name": "employers one source group",
    "parent": 118,
    "size": 1
  },
  {
    "id": 120,
    "name": "employers one source group inc",
    "parent": 118,
    "size": 1
  },
  {
    "id": 121,
    "name": "group 1 employment verification",
    "parent": 118,
    "size": 1
  },
  {
    "id": 122,
    "name": "group one employment verification",
    "parent": 118,
    "size": 1
  },
  {
    "id": 123,
    "name": "just works employment group",
    "parent": 118,
    "size": 1
  },
  {
    "id": 124,
    "name": "just works employment group llc",
    "parent": 118,
    "size": 1
  },
  {
    "id": 125,
    "name": "justworks employment group llc address",
    "parent": 118,
    "size": 1
  },
  {
    "id": 126,
    "name": "one source staffing inc",
    "parent": 118,
    "size": 1
  },
  {
    "id": 127,
    "name": "sunrise senior",
    "parent": 1
  },
  {
    "id": 128,
    "name": "city of sunrise employment",
    "parent": 127,
    "size": 1
  },
  {
    "id": 129,
    "name": "sunrise hospital employment",
    "parent": 127,
    "size": 1
  },
  {
    "id": 130,
    "name": "sunrise senior living employee benefits",
    "parent": 127,
    "size": 1
  },
  {
    "id": 131,
    "name": "sunrise senior living employee handbook",
    "parent": 127,
    "size": 1
  },
  {
    "id": 132,
    "name": "sunrise senior living employee login",
    "parent": 127,
    "size": 1
  },
  {
    "id": 133,
    "name": "sunrise senior living employee portal",
    "parent": 127,
    "size": 1
  },
  {
    "id": 134,
    "name": "sunrise senior living employee reviews",
    "parent": 127,
    "size": 1
  },
  {
    "id": 135,
    "name": "sunrise senior living employment",
    "parent": 127,
    "size": 1
  },
  {
    "id": 136,
    "name": "sunrise senior living payroll",
    "parent": 127,
    "size": 1
  },
  {
    "id": 137,
    "name": "sunrise senior living salary",
    "parent": 127,
    "size": 1
  },
  {
    "id": 138,
    "name": "payroll ohio",
    "parent": 1
  },
  {
    "id": 139,
    "name": "365 staffing toledo",
    "parent": 138,
    "size": 1
  },
  {
    "id": 140,
    "name": "cincinnati payroll services",
    "parent": 138,
    "size": 1
  },
  {
    "id": 141,
    "name": "city of watsonville employment",
    "parent": 138,
    "size": 1
  },
  {
    "id": 142,
    "name": "cleveland employment",
    "parent": 138,
    "size": 1
  },
  {
    "id": 143,
    "name": "employee management services cincinnati oh",
    "parent": 138,
    "size": 1
  },
  {
    "id": 144,
    "name": "employment in cleveland",
    "parent": 138,
    "size": 1
  },
  {
    "id": 145,
    "name": "employment in columbus",
    "parent": 138,
    "size": 1
  },
  {
    "id": 146,
    "name": "employment in columbus ohio",
    "parent": 138,
    "size": 1
  },
  {
    "id": 147,
    "name": "hartville ohio employment",
    "parent": 138,
    "size": 1
  },
  {
    "id": 148,
    "name": "impact employment solutions toledo oh",
    "parent": 138,
    "size": 1
  },
  {
    "id": 149,
    "name": "ohio professional employer organization",
    "parent": 138,
    "size": 1
  },
  {
    "id": 150,
    "name": "payroll companies in cleveland ohio",
    "parent": 138,
    "size": 1
  },
  {
    "id": 151,
    "name": "augusta employment",
    "parent": 1
  },
  {
    "id": 152,
    "name": "augusta county employment",
    "parent": 151,
    "size": 1
  },
  {
    "id": 153,
    "name": "augusta employment agencies",
    "parent": 151,
    "size": 1
  },
  {
    "id": 154,
    "name": "augusta national employment",
    "parent": 151,
    "size": 1
  },
  {
    "id": 155,
    "name": "augusta payroll",
    "parent": 151,
    "size": 1
  },
  {
    "id": 156,
    "name": "augusta regional airport employment",
    "parent": 151,
    "size": 1
  },
  {
    "id": 157,
    "name": "augusta university employment",
    "parent": 151,
    "size": 1
  },
  {
    "id": 158,
    "name": "augusta university payroll",
    "parent": 151,
    "size": 1
  },
  {
    "id": 159,
    "name": "payroll plus augusta",
    "parent": 151,
    "size": 1
  },
  {
    "id": 160,
    "name": "payroll plus augusta ga",
    "parent": 151,
    "size": 1
  },
  {
    "id": 161,
    "name": "Sub-Clusters Remaining",
    "parent": 1
  },
  {
    "id": 162,
    "name": "2",
    "parent": 161,
    "size": 1
  },
  {
    "id": 163,
    "name": "Total Rows Remaining",
    "parent": 1
  },
  {
    "id": 164,
    "name": "39",
    "parent": 163,
    "size": 1
  }
]