[
  {
    "id": 1,
    "name": "california"
  },
  {
    "id": 2,
    "name": "california taxes",
    "parent": 1
  },
  {
    "id": 3,
    "name": "100000 after taxes california",
    "parent": 2,
    "size": 1
  },
  {
    "id": 4,
    "name": "100k a year after taxes california",
    "parent": 2,
    "size": 1
  },
  {
    "id": 5,
    "name": "100k after tax california",
    "parent": 2,
    "size": 1
  },
  {
    "id": 6,
    "name": "100k after taxes california",
    "parent": 2,
    "size": 1
  },
  {
    "id": 7,
    "name": "100k in california after taxes",
    "parent": 2,
    "size": 1
  },
  {
    "id": 8,
    "name": "100k salary after taxes california",
    "parent": 2,
    "size": 1
  },
  {
    "id": 9,
    "name": "120000 after taxes california",
    "parent": 2,
    "size": 1
  },
  {
    "id": 10,
    "name": "120k salary after taxes california",
    "parent": 2,
    "size": 1
  },
  {
    "id": 11,
    "name": "125k after taxes california",
    "parent": 2,
    "size": 1
  },
  {
    "id": 12,
    "name": "125k salary after taxes california",
    "parent": 2,
    "size": 1
  },
  {
    "id": 13,
    "name": "130k after taxes california",
    "parent": 2,
    "size": 1
  },
  {
    "id": 14,
    "name": "135k after taxes california",
    "parent": 2,
    "size": 1
  },
  {
    "id": 15,
    "name": "cal connect",
    "parent": 1
  },
  {
    "id": 16,
    "name": "cal connect employee",
    "parent": 15,
    "size": 1
  },
  {
    "id": 17,
    "name": "cal connect employees",
    "parent": 15,
    "size": 1
  },
  {
    "id": 18,
    "name": "cal employee connect app",
    "parent": 15,
    "size": 1
  },
  {
    "id": 19,
    "name": "cal employee connect w2",
    "parent": 15,
    "size": 1
  },
  {
    "id": 20,
    "name": "calsaver employer login",
    "parent": 15,
    "size": 1
  },
  {
    "id": 21,
    "name": "calsavers employer",
    "parent": 15,
    "size": 1
  },
  {
    "id": 22,
    "name": "calsavers employer login",
    "parent": 15,
    "size": 1
  },
  {
    "id": 23,
    "name": "calsavers employer requirements",
    "parent": 15,
    "size": 1
  },
  {
    "id": 24,
    "name": "calsavers employers",
    "parent": 15,
    "size": 1
  },
  {
    "id": 25,
    "name": "calsavers for employers",
    "parent": 15,
    "size": 1
  },
  {
    "id": 26,
    "name": "employee cal connect",
    "parent": 15,
    "size": 1
  },
  {
    "id": 27,
    "name": "california new",
    "parent": 1
  },
  {
    "id": 28,
    "name": "california employee write up form",
    "parent": 27,
    "size": 1
  },
  {
    "id": 29,
    "name": "california new employee forms",
    "parent": 27,
    "size": 1
  },
  {
    "id": 30,
    "name": "california new hire forms",
    "parent": 27,
    "size": 1
  },
  {
    "id": 31,
    "name": "california new hire forms 2023",
    "parent": 27,
    "size": 1
  },
  {
    "id": 32,
    "name": "california new hire notice requirements",
    "parent": 27,
    "size": 1
  },
  {
    "id": 33,
    "name": "california new hire notice requirements 2023",
    "parent": 27,
    "size": 1
  },
  {
    "id": 34,
    "name": "california new hire report",
    "parent": 27,
    "size": 1
  },
  {
    "id": 35,
    "name": "california new hire reporting",
    "parent": 27,
    "size": 1
  },
  {
    "id": 36,
    "name": "new employee forms california",
    "parent": 27,
    "size": 1
  },
  {
    "id": 37,
    "name": "new hire paperwork california",
    "parent": 27,
    "size": 1
  },
  {
    "id": 38,
    "name": "new hire reporting ca",
    "parent": 27,
    "size": 1
  },
  {
    "id": 39,
    "name": "state of california new hire forms",
    "parent": 27,
    "size": 1
  },
  {
    "id": 40,
    "name": "california employment",
    "parent": 1
  },
  {
    "id": 41,
    "name": "california employer registration",
    "parent": 40,
    "size": 1
  },
  {
    "id": 42,
    "name": "california job application form",
    "parent": 40,
    "size": 1
  },
  {
    "id": 43,
    "name": "employment application california",
    "parent": 40,
    "size": 1
  },
  {
    "id": 44,
    "name": "employment application california pdf",
    "parent": 40,
    "size": 1
  },
  {
    "id": 45,
    "name": "employment application form california",
    "parent": 40,
    "size": 1
  },
  {
    "id": 46,
    "name": "employment verification california",
    "parent": 40,
    "size": 1
  },
  {
    "id": 47,
    "name": "state of california check verification",
    "parent": 40,
    "size": 1
  },
  {
    "id": 48,
    "name": "state of california employment application",
    "parent": 40,
    "size": 1
  },
  {
    "id": 49,
    "name": "state of california employment verification",
    "parent": 40,
    "size": 1
  },
  {
    "id": 50,
    "name": "california employee",
    "parent": 1
  },
  {
    "id": 51,
    "name": "california employee privacy laws",
    "parent": 50,
    "size": 1
  },
  {
    "id": 52,
    "name": "california employment laws by company size",
    "parent": 50,
    "size": 1
  },
  {
    "id": 53,
    "name": "california household employee taxes",
    "parent": 50,
    "size": 1
  },
  {
    "id": 54,
    "name": "california household employer guide",
    "parent": 50,
    "size": 1
  },
  {
    "id": 55,
    "name": "california labor laws remote workers",
    "parent": 50,
    "size": 1
  },
  {
    "id": 56,
    "name": "california pto laws exempt employees",
    "parent": 50,
    "size": 1
  },
  {
    "id": 57,
    "name": "california state employee travel restrictions",
    "parent": 50,
    "size": 1
  },
  {
    "id": 58,
    "name": "can an employee refuse to travel for work",
    "parent": 50,
    "size": 1
  },
  {
    "id": 59,
    "name": "do california labor laws apply to out-of-state employers",
    "parent": 50,
    "size": 1
  },
  {
    "id": 60,
    "name": "out-of-state employers with employees in california",
    "parent": 50,
    "size": 1
  },
  {
    "id": 61,
    "name": "out-of-state employers with remote employees in california",
    "parent": 50,
    "size": 1
  },
  {
    "id": 62,
    "name": "remote employee in california",
    "parent": 50,
    "size": 1
  },
  {
    "id": 63,
    "name": "state another",
    "parent": 1
  },
  {
    "id": 64,
    "name": "can federal employees telework from another state",
    "parent": 63,
    "size": 1
  },
  {
    "id": 65,
    "name": "does having an employee in a state create nexus",
    "parent": 63,
    "size": 1
  },
  {
    "id": 66,
    "name": "employee working remotely in another state",
    "parent": 63,
    "size": 1
  },
  {
    "id": 67,
    "name": "employee works from home in another state",
    "parent": 63,
    "size": 1
  },
  {
    "id": 68,
    "name": "employment application laws by state",
    "parent": 63,
    "size": 1
  },
  {
    "id": 69,
    "name": "if my employer is in another state",
    "parent": 63,
    "size": 1
  },
  {
    "id": 70,
    "name": "out of state employee",
    "parent": 63,
    "size": 1
  },
  {
    "id": 71,
    "name": "out of state employees",
    "parent": 63,
    "size": 1
  },
  {
    "id": 72,
    "name": "state employment laws chart",
    "parent": 63,
    "size": 1
  },
  {
    "id": 73,
    "name": "Sub-Clusters Remaining",
    "parent": 1
  },
  {
    "id": 74,
    "name": "0",
    "parent": 73,
    "size": 1
  },
  {
    "id": 75,
    "name": "Total Rows Remaining",
    "parent": 1
  },
  {
    "id": 76,
    "name": "47",
    "parent": 75,
    "size": 1
  }
]