[
  {
    "id": 1,
    "name": "calculate"
  },
  {
    "id": 2,
    "name": "ot calculate",
    "parent": 1
  },
  {
    "id": 3,
    "name": "calculate ot",
    "parent": 2,
    "size": 1
  },
  {
    "id": 4,
    "name": "calculation ot",
    "parent": 2,
    "size": 1
  },
  {
    "id": 5,
    "name": "how is ot calculated",
    "parent": 2,
    "size": 1
  },
  {
    "id": 6,
    "name": "how to calculate ot",
    "parent": 2,
    "size": 1
  },
  {
    "id": 7,
    "name": "how to calculate ot in excel",
    "parent": 2,
    "size": 1
  },
  {
    "id": 8,
    "name": "how to calculate ot rate",
    "parent": 2,
    "size": 1
  },
  {
    "id": 9,
    "name": "ot calculation",
    "parent": 2,
    "size": 1
  },
  {
    "id": 10,
    "name": "ot factor",
    "parent": 2,
    "size": 1
  },
  {
    "id": 11,
    "name": "ot rate calculation",
    "parent": 2,
    "size": 1
  },
  {
    "id": 12,
    "name": "check calculate",
    "parent": 1
  },
  {
    "id": 13,
    "name": "calculate my check",
    "parent": 12,
    "size": 1
  },
  {
    "id": 14,
    "name": "calculate your check",
    "parent": 12,
    "size": 1
  },
  {
    "id": 15,
    "name": "check calculater",
    "parent": 12,
    "size": 1
  },
  {
    "id": 16,
    "name": "check calculation",
    "parent": 12,
    "size": 1
  },
  {
    "id": 17,
    "name": "how do you calculate your check",
    "parent": 12,
    "size": 1
  },
  {
    "id": 18,
    "name": "how to calculate a check",
    "parent": 12,
    "size": 1
  },
  {
    "id": 19,
    "name": "how to calculate how much your check will be",
    "parent": 12,
    "size": 1
  },
  {
    "id": 20,
    "name": "how to calculate your check",
    "parent": 12,
    "size": 1
  },
  {
    "id": 21,
    "name": "calculate ppp",
    "parent": 1
  },
  {
    "id": 22,
    "name": "calculate ap",
    "parent": 21,
    "size": 1
  },
  {
    "id": 23,
    "name": "calculate pa",
    "parent": 21,
    "size": 1
  },
  {
    "id": 24,
    "name": "calculate ppp",
    "parent": 21,
    "size": 1
  },
  {
    "id": 25,
    "name": "how to calculate ppp",
    "parent": 21,
    "size": 1
  },
  {
    "id": 26,
    "name": "ppp calculation formula",
    "parent": 21,
    "size": 1
  },
  {
    "id": 27,
    "name": "ratio compa",
    "parent": 1
  },
  {
    "id": 28,
    "name": "calculate compa ratio",
    "parent": 27,
    "size": 1
  },
  {
    "id": 29,
    "name": "compa ratio calculation",
    "parent": 27,
    "size": 1
  },
  {
    "id": 30,
    "name": "compa-ratio calculation",
    "parent": 27,
    "size": 1
  },
  {
    "id": 31,
    "name": "how do you calculate compa ratio",
    "parent": 27,
    "size": 1
  },
  {
    "id": 32,
    "name": "ratio calculation",
    "parent": 27,
    "size": 1
  },
  {
    "id": 33,
    "name": "pto calculate",
    "parent": 1
  },
  {
    "id": 34,
    "name": "calculate pto accrual rate",
    "parent": 33,
    "size": 1
  },
  {
    "id": 35,
    "name": "how is pto calculated",
    "parent": 33,
    "size": 1
  },
  {
    "id": 36,
    "name": "how pto is calculated",
    "parent": 33,
    "size": 1
  },
  {
    "id": 37,
    "name": "how to calculate prorated pto",
    "parent": 33,
    "size": 1
  },
  {
    "id": 38,
    "name": "how to calculate pto accrual rate",
    "parent": 33,
    "size": 1
  },
  {
    "id": 39,
    "name": "how to calculate pto hours to days",
    "parent": 33,
    "size": 1
  },
  {
    "id": 40,
    "name": "pto calculation",
    "parent": 33,
    "size": 1
  },
  {
    "id": 41,
    "name": "pto calculator for hourly employees",
    "parent": 33,
    "size": 1
  },
  {
    "id": 42,
    "name": "pto calculator for salaried employees",
    "parent": 33,
    "size": 1
  },
  {
    "id": 43,
    "name": "Sub-Clusters Remaining",
    "parent": 1
  },
  {
    "id": 44,
    "name": "0",
    "parent": 43,
    "size": 1
  },
  {
    "id": 45,
    "name": "Total Rows Remaining",
    "parent": 1
  }
]