[
  {
    "id": 1,
    "name": "much"
  },
  {
    "id": 2,
    "name": "much california",
    "parent": 1
  },
  {
    "id": 3,
    "name": "california state tax how much",
    "parent": 2,
    "size": 1
  },
  {
    "id": 4,
    "name": "california tax amount",
    "parent": 2,
    "size": 1
  },
  {
    "id": 5,
    "name": "how much after taxes california",
    "parent": 2,
    "size": 1
  },
  {
    "id": 6,
    "name": "how much are ca state taxes",
    "parent": 2,
    "size": 1
  },
  {
    "id": 7,
    "name": "how much are california state income taxes",
    "parent": 2,
    "size": 1
  },
  {
    "id": 8,
    "name": "how much are california state taxes",
    "parent": 2,
    "size": 1
  },
  {
    "id": 9,
    "name": "how much are california taxes",
    "parent": 2,
    "size": 1
  },
  {
    "id": 10,
    "name": "how much are income taxes in california",
    "parent": 2,
    "size": 1
  },
  {
    "id": 11,
    "name": "how much are state taxes in california",
    "parent": 2,
    "size": 1
  },
  {
    "id": 12,
    "name": "how much are taxes in california",
    "parent": 2,
    "size": 1
  },
  {
    "id": 13,
    "name": "how much california state income tax",
    "parent": 2,
    "size": 1
  },
  {
    "id": 14,
    "name": "how much california tax",
    "parent": 2,
    "size": 1
  },
  {
    "id": 15,
    "name": "much calculator",
    "parent": 1
  },
  {
    "id": 16,
    "name": "how much after taxes calculator",
    "parent": 15,
    "size": 1
  },
  {
    "id": 17,
    "name": "how much do i have to pay in taxes calculator",
    "parent": 15,
    "size": 1
  },
  {
    "id": 18,
    "name": "how much do i make after taxes calculator",
    "parent": 15,
    "size": 1
  },
  {
    "id": 19,
    "name": "how much do i owe in taxes calculator",
    "parent": 15,
    "size": 1
  },
  {
    "id": 20,
    "name": "how much do i owe the irs calculator",
    "parent": 15,
    "size": 1
  },
  {
    "id": 21,
    "name": "how much federal tax calculator",
    "parent": 15,
    "size": 1
  },
  {
    "id": 22,
    "name": "how much federal tax should i pay calculator",
    "parent": 15,
    "size": 1
  },
  {
    "id": 23,
    "name": "how much i pay tax calculator",
    "parent": 15,
    "size": 1
  },
  {
    "id": 24,
    "name": "how much income tax calculator",
    "parent": 15,
    "size": 1
  },
  {
    "id": 25,
    "name": "how much income tax do i pay calculator",
    "parent": 15,
    "size": 1
  },
  {
    "id": 26,
    "name": "how much income tax will i pay calculator",
    "parent": 15,
    "size": 1
  },
  {
    "id": 27,
    "name": "how much should i get back in taxes calculator",
    "parent": 15,
    "size": 1
  },
  {
    "id": 28,
    "name": "paycheck california",
    "parent": 1
  },
  {
    "id": 29,
    "name": "california tax deductions on paycheck",
    "parent": 28,
    "size": 1
  },
  {
    "id": 30,
    "name": "california tax on paycheck",
    "parent": 28,
    "size": 1
  },
  {
    "id": 31,
    "name": "california taxes from paycheck",
    "parent": 28,
    "size": 1
  },
  {
    "id": 32,
    "name": "california taxes on paycheck",
    "parent": 28,
    "size": 1
  },
  {
    "id": 33,
    "name": "california taxes out of paycheck",
    "parent": 28,
    "size": 1
  },
  {
    "id": 34,
    "name": "how much are taxes in california paycheck",
    "parent": 28,
    "size": 1
  },
  {
    "id": 35,
    "name": "how much does california take out of your paycheck",
    "parent": 28,
    "size": 1
  },
  {
    "id": 36,
    "name": "how much does california tax your paycheck",
    "parent": 28,
    "size": 1
  },
  {
    "id": 37,
    "name": "how much is ca tax on paycheck",
    "parent": 28,
    "size": 1
  },
  {
    "id": 38,
    "name": "how much is california tax on paycheck",
    "parent": 28,
    "size": 1
  },
  {
    "id": 39,
    "name": "how much is taken out of paycheck in california",
    "parent": 28,
    "size": 1
  },
  {
    "id": 40,
    "name": "how much is tax on paycheck in california",
    "parent": 28,
    "size": 1
  },
  {
    "id": 41,
    "name": "much take",
    "parent": 1
  },
  {
    "id": 42,
    "name": "how much do they take for taxes",
    "parent": 41,
    "size": 1
  },
  {
    "id": 43,
    "name": "how much do they take in taxes",
    "parent": 41,
    "size": 1
  },
  {
    "id": 44,
    "name": "how much do they take off for taxes",
    "parent": 41,
    "size": 1
  },
  {
    "id": 45,
    "name": "how much do they take out for taxes",
    "parent": 41,
    "size": 1
  },
  {
    "id": 46,
    "name": "how much do they take out in taxes",
    "parent": 41,
    "size": 1
  },
  {
    "id": 47,
    "name": "how much do they take out of taxes",
    "parent": 41,
    "size": 1
  },
  {
    "id": 48,
    "name": "how much money do they take out for taxes",
    "parent": 41,
    "size": 1
  },
  {
    "id": 49,
    "name": "how much money do they take out in taxes",
    "parent": 41,
    "size": 1
  },
  {
    "id": 50,
    "name": "how much tax do they take",
    "parent": 41,
    "size": 1
  },
  {
    "id": 51,
    "name": "how much tax they take out",
    "parent": 41,
    "size": 1
  },
  {
    "id": 52,
    "name": "how much taxes do they take out",
    "parent": 41,
    "size": 1
  },
  {
    "id": 53,
    "name": "how much taxes will they take out",
    "parent": 41,
    "size": 1
  },
  {
    "id": 54,
    "name": "Sub-Clusters Remaining",
    "parent": 1
  },
  {
    "id": 55,
    "name": "0",
    "parent": 54,
    "size": 1
  },
  {
    "id": 56,
    "name": "Total Rows Remaining",
    "parent": 1
  },
  {
    "id": 57,
    "name": "85",
    "parent": 56,
    "size": 1
  }
]